{
    "title": "插件文档",
    "description": "Minecraft 插件文档中心",
    "author": "Your Name",
    "language": "zh-hans",
    "plugins": [
        "chapter-fold",
        "alerts",
        "flexible-alerts"
    ],
    "pluginsConfig": {
        "theme-default": {
            "showLevel": true
        },
        "flexible-alerts": {
            "style": "callout",
            "comment": {
                "label": "Comment",
                "icon": "fa fa-comments",
                "className": "info"
            }
        }
    },
    "styles": {
        "website": "styles/website.css"
    }
} 